AndroidShejiZhinan44/README.md
AndroidShejiZhinan44/__init__.py
AndroidShejiZhinan44/__main__.py
AndroidShejiZhinan44/file.epub
AndroidShejiZhinan44/index.html
AndroidShejiZhinan44/css/__init__.py
AndroidShejiZhinan44/css/annotations.css
AndroidShejiZhinan44/css/main.css
AndroidShejiZhinan44/css/normalize.css
AndroidShejiZhinan44/css/popup.css
AndroidShejiZhinan44/font/__init__.py
AndroidShejiZhinan44/font/fontello.eot
AndroidShejiZhinan44/font/fontello.svg
AndroidShejiZhinan44/font/fontello.ttf
AndroidShejiZhinan44/font/fontello.woff
AndroidShejiZhinan44/img/__init__.py
AndroidShejiZhinan44/img/annotator-glyph-sprite.png
AndroidShejiZhinan44/img/annotator-icon-sprite.png
AndroidShejiZhinan44/img/apple-touch-icon.png
AndroidShejiZhinan44/img/cancelfullscreen.png
AndroidShejiZhinan44/img/close.png
AndroidShejiZhinan44/img/fullscreen.png
AndroidShejiZhinan44/img/loader.gif
AndroidShejiZhinan44/img/menu-icon.png
AndroidShejiZhinan44/img/save.png
AndroidShejiZhinan44/img/saved.png
AndroidShejiZhinan44/img/settings-s.png
AndroidShejiZhinan44/img/settings.png
AndroidShejiZhinan44/img/star.png
AndroidShejiZhinan44/js/__init__.py
AndroidShejiZhinan44/js/epub.js
AndroidShejiZhinan44/js/epub.min.js
AndroidShejiZhinan44/js/epub.min.map
AndroidShejiZhinan44/js/hooks.min.js
AndroidShejiZhinan44/js/hooks.min.map
AndroidShejiZhinan44/js/reader.js
AndroidShejiZhinan44/js/reader.js.map
AndroidShejiZhinan44/js/reader.min.js
AndroidShejiZhinan44/js/reader.min.map
AndroidShejiZhinan44/js/hooks/__init__.py
AndroidShejiZhinan44/js/hooks/extensions/__init__.py
AndroidShejiZhinan44/js/hooks/extensions/highlight.js
AndroidShejiZhinan44/js/libs/__init__.py
AndroidShejiZhinan44/js/libs/jquery.min.js
AndroidShejiZhinan44/js/libs/localforage.min.js
AndroidShejiZhinan44/js/libs/screenfull.js
AndroidShejiZhinan44/js/libs/screenfull.min.js
AndroidShejiZhinan44/js/libs/zip.min.js
AndroidShejiZhinan44/js/plugins/__init__.py
AndroidShejiZhinan44/js/plugins/hypothesis.js
android_sheji_zhinan_4_4-2024.2.29.0.dist-info/METADATA
android_sheji_zhinan_4_4-2024.2.29.0.dist-info/WHEEL
android_sheji_zhinan_4_4-2024.2.29.0.dist-info/entry_points.txt
android_sheji_zhinan_4_4-2024.2.29.0.dist-info/top_level.txt
android_sheji_zhinan_4_4-2024.2.29.0.dist-info/RECORD
